{"is_source_file": true, "description": "Simple md file", "external_files": [], "external_methods": [], "published": [], "calls": [], "search-terms": [], "classes": [], "methods": [], "state": 2, "file_id": 1, "knowledge_revision": 3, "git_revision": "970ca7a1c20011bf96a04bc480f1d10ed00c9910", "filename": "README.md", "hash": "e367c46487525c35a5d3b76b0b2b4cbf", "format-version": 4, "code-base-name": "https://github.com/kavia-common/flutter-app---tel-5360-5406.git:kavia-main", "revision_history": [{"3": "970ca7a1c20011bf96a04bc480f1d10ed00c9910"}]}